math_spec_mapping/__init__.py
math_spec_mapping/schema.py
math_spec_mapping/schema.schema.json
math_spec_mapping/Classes/ActionTransmissionChannel.py
math_spec_mapping/Classes/Block.py
math_spec_mapping/Classes/BoundaryAction.py
math_spec_mapping/Classes/ControlAction.py
math_spec_mapping/Classes/Entity.py
math_spec_mapping/Classes/MathSpec.py
math_spec_mapping/Classes/Mechanism.py
math_spec_mapping/Classes/Metric.py
math_spec_mapping/Classes/Parameter.py
math_spec_mapping/Classes/Policy.py
math_spec_mapping/Classes/Space.py
math_spec_mapping/Classes/State.py
math_spec_mapping/Classes/StateUpdateTransmissionChannel.py
math_spec_mapping/Classes/StatefulMetric.py
math_spec_mapping/Classes/Type.py
math_spec_mapping/Classes/__init__.py
math_spec_mapping/Convenience/__init__.py
math_spec_mapping/Convenience/cadCAD.py
math_spec_mapping/Convenience/documentation.py
math_spec_mapping/Convenience/github.py
math_spec_mapping/Convenience/starter.py
math_spec_mapping/Load/__init__.py
math_spec_mapping/Load/action_transmission_channel.py
math_spec_mapping/Load/boundary_actions.py
math_spec_mapping/Load/control_actions.py
math_spec_mapping/Load/displays.py
math_spec_mapping/Load/entities.py
math_spec_mapping/Load/general.py
math_spec_mapping/Load/implementations.py
math_spec_mapping/Load/load.py
math_spec_mapping/Load/mechanism.py
math_spec_mapping/Load/metrics.py
math_spec_mapping/Load/parameters.py
math_spec_mapping/Load/policy.py
math_spec_mapping/Load/spaces.py
math_spec_mapping/Load/spec_tree.py
math_spec_mapping/Load/state_update_transmission_channels.py
math_spec_mapping/Load/stateful_metrics.py
math_spec_mapping/Load/states.py
math_spec_mapping/Load/type.py
math_spec_mapping/Load/wiring.py
math_spec_mapping/Reports/__init__.py
math_spec_mapping/Reports/advanced.py
math_spec_mapping/Reports/boundary_actions.py
math_spec_mapping/Reports/control_actions.py
math_spec_mapping/Reports/general.py
math_spec_mapping/Reports/html.py
math_spec_mapping/Reports/markdown.py
math_spec_mapping-0.4.4.dist-info/licenses/LICENSE
math_spec_mapping-0.4.4.dist-info/METADATA
math_spec_mapping-0.4.4.dist-info/WHEEL
math_spec_mapping-0.4.4.dist-info/top_level.txt
math_spec_mapping-0.4.4.dist-info/RECORD
