Metadata-Version: 2.4
Name: math-spec-mapping
Version: 0.4.4
Summary: A library for easy mapping of mathematical specifications.
Author-email: Sean McOwen <Sean@Block.Science>
Classifier: Programming Language :: Python :: 3
Classifier: License :: OSI Approved :: MIT License
Classifier: Operating System :: OS Independent
Requires-Python: >=3.7
License-File: LICENSE
Requires-Dist: graphviz>=0.20.1
Requires-Dist: ipython>=7.7.0
Requires-Dist: pandas>=1.4
Requires-Dist: jsonschema>=4.21.1
Requires-Dist: PyGithub==2.5.0
Requires-Dist: python-dotenv>=1.0.0
Requires-Dist: pypandoc>=1.15
Dynamic: license-file
